django_commento_sso/__init__.py
django_commento_sso/conf.py
django_commento_sso/urls.py
django_commento_sso/utils.py
django_commento_sso/views.py
django_commento_sso/wsgi.py
django_commento_sso-0.2.dist-info/LICENSE
django_commento_sso-0.2.dist-info/METADATA
django_commento_sso-0.2.dist-info/WHEEL
django_commento_sso-0.2.dist-info/top_level.txt
django_commento_sso-0.2.dist-info/RECORD
